imio.migrator-1.35-py3.11-nspkg.pth
imio/migrator/__init__.py
imio/migrator/migrator.py
imio/migrator/testing.py
imio/migrator/testing.zcml
imio/migrator/utils.py
imio/migrator/tests/__init__.py
imio.migrator-1.35.dist-info/METADATA
imio.migrator-1.35.dist-info/WHEEL
imio.migrator-1.35.dist-info/entry_points.txt
imio.migrator-1.35.dist-info/namespace_packages.txt
imio.migrator-1.35.dist-info/top_level.txt
imio.migrator-1.35.dist-info/RECORD
