Metadata-Version: 2.1
Name: imio.migrator
Version: 1.35
Summary: Migration helper tool
Home-page: https://github.com/imio/imio.migrator
Download-URL: https://pypi.org/project/imio.migrator
Author: IMIO
Author-email: dev@imio.be
License: GPL
Keywords: migration helpers
Classifier: Development Status :: 5 - Production/Stable
Classifier: Environment :: Web Environment
Classifier: Framework :: Plone
Classifier: Framework :: Plone :: 4.3
Classifier: License :: OSI Approved :: GNU General Public License v2 (GPLv2)
Classifier: Operating System :: OS Independent
Classifier: Programming Language :: Python
Classifier: Programming Language :: Python :: 2.7
Requires-Dist: Plone
Requires-Dist: imio.helpers >=1.0.0
Requires-Dist: imio.pyutils >=0.20
Requires-Dist: setuptools
Provides-Extra: test
Requires-Dist: plone.app.testing ; extra == 'test'
